odoo/addons/edi/README.rst
odoo/addons/edi/__init__.py
odoo/addons/edi/__manifest__.py
odoo/addons/edi/exceptions.py
odoo/addons/edi/utils.py
odoo/addons/edi/components/__init__.py
odoo/addons/edi/components/base.py
odoo/addons/edi/components/base_input.py
odoo/addons/edi/components/base_output.py
odoo/addons/edi/components/base_validate.py
odoo/addons/edi/data/cron.xml
odoo/addons/edi/data/job_channel.xml
odoo/addons/edi/data/job_function.xml
odoo/addons/edi/data/sequence.xml
odoo/addons/edi/demo/edi_backend_demo.xml
odoo/addons/edi/i18n/edi.pot
odoo/addons/edi/models/__init__.py
odoo/addons/edi/models/edi_backend.py
odoo/addons/edi/models/edi_backend_type.py
odoo/addons/edi/models/edi_exchange_consumer_mixin.py
odoo/addons/edi/models/edi_exchange_record.py
odoo/addons/edi/models/edi_exchange_type.py
odoo/addons/edi/readme/CONFIGURE.rst
odoo/addons/edi/readme/CONTRIBUTORS.rst
odoo/addons/edi/readme/DESCRIPTION.rst
odoo/addons/edi/readme/USAGE.rst
odoo/addons/edi/security/ir_model_access.xml
odoo/addons/edi/security/res_groups.xml
odoo/addons/edi/static/description/icon.png
odoo/addons/edi/static/description/icon.svg
odoo/addons/edi/static/description/index.html
odoo/addons/edi/static/src/js/widget_edi.js
odoo/addons/edi/static/src/xml/widget_edi.xml
odoo/addons/edi/templates/assets.xml
odoo/addons/edi/templates/exchange_chatter_msg.xml
odoo/addons/edi/templates/exchange_mixin_buttons.xml
odoo/addons/edi/tests/__init__.py
odoo/addons/edi/tests/common.py
odoo/addons/edi/tests/fake_components.py
odoo/addons/edi/tests/fake_models.py
odoo/addons/edi/tests/test_backend_base.py
odoo/addons/edi/tests/test_backend_input.py
odoo/addons/edi/tests/test_backend_jobs.py
odoo/addons/edi/tests/test_backend_output.py
odoo/addons/edi/tests/test_backend_process.py
odoo/addons/edi/tests/test_backend_type.py
odoo/addons/edi/tests/test_backend_validate.py
odoo/addons/edi/tests/test_component_match.py
odoo/addons/edi/tests/test_consumer_mixin.py
odoo13_addon_edi-13.0.1.24.0.dist-info/METADATA
odoo13_addon_edi-13.0.1.24.0.dist-info/WHEEL
odoo13_addon_edi-13.0.1.24.0.dist-info/top_level.txt
odoo13_addon_edi-13.0.1.24.0.dist-info/RECORD
