Metadata-Version: 2.1
Name: odoo13-addon-edi
Version: 13.0.1.24.0
Summary: Define backends, exchange types, exchange records, basic automation and views for handling EDI exchanges.
Home-page: https://github.com/OCA/edi
Author: ACSONE,Odoo Community Association (OCA)
Author-email: support@odoo-community.org
License: LGPL-3
Platform: UNKNOWN
Classifier: Programming Language :: Python
Classifier: Framework :: Odoo
Classifier: Framework :: Odoo :: 13.0
Classifier: License :: OSI Approved :: GNU Lesser General Public License v3 (LGPLv3)
Classifier: Development Status :: 4 - Beta
Requires-Python: >=3.5
Requires-Dist: odoo13-addon-base-edi
Requires-Dist: odoo13-addon-component-event
Requires-Dist: odoo13-addon-queue-job
Requires-Dist: odoo (<13.1dev,>=13.0a)
Requires-Dist: pyyaml
